{
  "slug": "egyptian-ar-tetradrachm",
  "category": "egyptian",
  "ruler": null,
  "ruler_normalized": null,
  "dynasty": null,
  "ruler_dates": null,
  "ruler_rarity": null,
  "denomination": "AR Tetradrachm",
  "metal": "silver",
  "sale_count": 12,
  "realized_count": 12,
  "fixed_price_count": 0,
  "ngc_verified_count": 0,
  "price_range_usd": {
    "min": 480.0,
    "max": 3600.0
  },
  "median_price_usd": 1320.0,
  "last_sale_date": "2022-11-04",
  "grade_distribution": {
    "MS": 9,
    "AU": 2,
    "VF": 1
  },
  "thumbnail_url": "https://dyn1.heritagestatic.com/ha?p=2-6-7-2-5-26725375&w=120&h=300&it=product",
  "median_weight_g": null,
  "top_strike_score": 5,
  "top_surface_score": 4,
  "top_grade_numeric": 5,
  "dominant_service": "ngc",
  "series": null,
  "date_struck": null,
  "mint_mark": null,
  "sales": [
    {
      "id": "heritage-cfd071f0a739",
      "source": "heritage",
      "listing_type": "auction_realized",
      "lot_url": "https://coins.ha.com/itm/ancients/greek/ancients-near-east-or-egypt-ca-5th-4th-centuries-bc-ar-tetradrachm-24mm-1705-gm-1h-ngc-ms-5-5-4-5/a/3102-32190.s?ic4=ListView-ShortDescription-071515",
      "title": "Ancients: NEAR EAST or EGYPT. Ca. 5th-4th centuries BC.\nAR tetradrachm (24mm, 17.05 gm, 1h). NGC MS 5/5 - 4/5.",
      "description": "Auction 3102 | Lot 32190 \u00bb Ancient Coins \u00bb Greek",
      "hammer_price_usd": 1020.0,
      "currency_original": "USD",
      "price_original": 1020.0,
      "buyers_premium_included": false,
      "sale_date": "2022-11-04",
      "image_url": "https://dyn1.heritagestatic.com/ha?p=2-6-7-2-5-26725375&w=120&h=300&it=product",
      "ngc": {
        "verified": false,
        "cert_number": null,
        "grade": "MS",
        "grade_numeric": 5,
        "strike_score": 5,
        "surface_score": 4,
        "details_grade": null,
        "certification_url": null,
        "grading_service": "ngc"
      },
      "metadata": {
        "mint": "",
        "weight_g": null,
        "diameter_mm": null,
        "obverse_desc": null,
        "reverse_desc": null
      }
    },
    {
      "id": "heritage-8738776112bb",
      "source": "heritage",
      "listing_type": "auction_realized",
      "lot_url": "https://coins.ha.com/itm/ancients/greek/ancients-near-east-or-egypt-ca-5th-4th-centuries-bc-ar-tetradrachm-27mm-1761-gm-8h-ngc-ms-4-5-4-5-die-shift/a/3102-32191.s?ic4=ListView-ShortDescription-071515",
      "title": "Ancients: NEAR EAST or EGYPT. Ca. 5th-4th centuries BC.\nAR tetradrachm (27mm, 17.61 gm, 8h). NGC MS 4/5 - 4/5, die\nshift.",
      "description": "Auction 3102 | Lot 32191 \u00bb Ancient Coins \u00bb Greek",
      "hammer_price_usd": 990.0,
      "currency_original": "USD",
      "price_original": 990.0,
      "buyers_premium_included": false,
      "sale_date": "2022-11-04",
      "image_url": "https://dyn1.heritagestatic.com/ha?p=2-6-7-9-1-26791669&w=120&h=300&it=product",
      "ngc": {
        "verified": false,
        "cert_number": null,
        "grade": "MS",
        "grade_numeric": 4,
        "strike_score": 4,
        "surface_score": 4,
        "details_grade": null,
        "certification_url": null,
        "grading_service": "ngc"
      },
      "metadata": {
        "mint": "",
        "weight_g": null,
        "diameter_mm": null,
        "obverse_desc": null,
        "reverse_desc": null
      }
    },
    {
      "id": "heritage-80b718c6ee64",
      "source": "heritage",
      "listing_type": "auction_realized",
      "lot_url": "https://coins.ha.com/itm/ancients/greek/ancients-near-east-or-egypt-ca-5th-4th-centuries-bc-ar-tetradrachm-25mm-1713-gm-8h-ngc-ms-5-5-4-5/a/3095-35037.s?ic4=ListView-ShortDescription-071515",
      "title": "Ancients: NEAR EAST or EGYPT. Ca. 5th-4th centuries BC.\nAR tetradrachm (25mm, 17.13 gm, 8h). NGC MS 5/5 - 4/5.",
      "description": "Auction 3095 | Lot 35037 \u00bb Ancient Coins \u00bb Greek",
      "hammer_price_usd": 1320.0,
      "currency_original": "USD",
      "price_original": 1320.0,
      "buyers_premium_included": false,
      "sale_date": "2021-12-13",
      "image_url": "https://dyn1.heritagestatic.com/ha?p=2-5-0-2-3-25023871&w=120&h=300&it=product",
      "ngc": {
        "verified": false,
        "cert_number": null,
        "grade": "MS",
        "grade_numeric": 5,
        "strike_score": 5,
        "surface_score": 4,
        "details_grade": null,
        "certification_url": null,
        "grading_service": "ngc"
      },
      "metadata": {
        "mint": "",
        "weight_g": null,
        "diameter_mm": null,
        "obverse_desc": null,
        "reverse_desc": null
      }
    },
    {
      "id": "heritage-ae8912465b5f",
      "source": "heritage",
      "listing_type": "auction_realized",
      "lot_url": "https://coins.ha.com/itm/ancients/greek/ancients-near-east-or-egypt-ca-5th-4th-centuries-bc-ar-tetradrachm-25mm-1701-gm-12h-ngc-ms-5-5-4-5/a/3093-31100.s?ic4=ListView-ShortDescription-071515",
      "title": "Ancients: NEAR EAST or EGYPT. Ca. 5th-4th centuries BC.\nAR tetradrachm (25mm, 17.01 gm, 12h). NGC MS 5/5 - 4/5.",
      "description": "Auction 3093 | Lot 31100 \u00bb Ancient Coins \u00bb Greek",
      "hammer_price_usd": 2100.0,
      "currency_original": "USD",
      "price_original": 2100.0,
      "buyers_premium_included": false,
      "sale_date": "2021-10-29",
      "image_url": "https://dyn1.heritagestatic.com/ha?p=2-4-7-0-1-24701567&w=120&h=300&it=product",
      "ngc": {
        "verified": false,
        "cert_number": null,
        "grade": "MS",
        "grade_numeric": 5,
        "strike_score": 5,
        "surface_score": 4,
        "details_grade": null,
        "certification_url": null,
        "grading_service": "ngc"
      },
      "metadata": {
        "mint": "",
        "weight_g": null,
        "diameter_mm": null,
        "obverse_desc": null,
        "reverse_desc": null
      }
    },
    {
      "id": "heritage-ea275f42c45c",
      "source": "heritage",
      "listing_type": "auction_realized",
      "lot_url": "https://coins.ha.com/itm/ancients/greek/ancients-near-east-or-egypt-ca-5th-4th-centuries-bc-ar-tetradrachm-24mm-1704-gm-5h-ngc-ms-5-5-4-5/a/3094-34144.s?ic4=ListView-ShortDescription-071515",
      "title": "Ancients: NEAR EAST or EGYPT. Ca. 5th-4th centuries BC.\nAR tetradrachm (24mm, 17.04 gm, 5h). NGC MS 5/5 - 4/5.",
      "description": "Auction 3094 | Lot 34144 \u00bb Ancient Coins \u00bb Greek",
      "hammer_price_usd": 2100.0,
      "currency_original": "USD",
      "price_original": 2100.0,
      "buyers_premium_included": false,
      "sale_date": "2021-08-20",
      "image_url": "https://dyn1.heritagestatic.com/ha?p=2-4-3-0-0-24300729&w=120&h=300&it=product",
      "ngc": {
        "verified": false,
        "cert_number": null,
        "grade": "MS",
        "grade_numeric": 5,
        "strike_score": 5,
        "surface_score": 4,
        "details_grade": null,
        "certification_url": null,
        "grading_service": "ngc"
      },
      "metadata": {
        "mint": "",
        "weight_g": null,
        "diameter_mm": null,
        "obverse_desc": null,
        "reverse_desc": null
      }
    },
    {
      "id": "heritage-a36a298019f2",
      "source": "heritage",
      "listing_type": "auction_realized",
      "lot_url": "https://coins.ha.com/itm/ancients/greek/ancients-near-east-or-egypt-ca-5th-4th-centuries-bc-ar-tetradrachm-24mm-1720-gm-12h-ngc-ms-5-5-4-5/a/3089-32132.s?ic4=ListView-ShortDescription-071515",
      "title": "Ancients:NEAR EAST or EGYPT. Ca. 5th-4th centuries BC.\nAR tetradrachm (24mm, 17.20 gm, 12h). NGC MS 5/5 - 4/5.",
      "description": "",
      "hammer_price_usd": 2280.0,
      "currency_original": "USD",
      "price_original": 2280.0,
      "buyers_premium_included": false,
      "sale_date": "2021-01-22",
      "image_url": "https://dyn1.heritagestatic.com/ha?p=2-3-2-2-7-23227778&w=120&h=300&it=product",
      "ngc": {
        "verified": false,
        "cert_number": null,
        "grade": "MS",
        "grade_numeric": 5,
        "strike_score": 5,
        "surface_score": 4,
        "details_grade": null,
        "certification_url": null,
        "grading_service": "ngc"
      },
      "metadata": {
        "mint": "",
        "weight_g": null,
        "diameter_mm": null,
        "obverse_desc": null,
        "reverse_desc": null
      }
    },
    {
      "id": "heritage-237e458fc5e5",
      "source": "heritage",
      "listing_type": "auction_realized",
      "lot_url": "https://coins.ha.com/itm/ancients/greek/ancients-near-east-or-egypt-ca-5th-4th-centuries-bc-ar-tetradrachm-26mm-1850-gm-3h-ngc-ms-5-5-4-5/a/3083-32117.s?ic4=ListView-ShortDescription-071515",
      "title": "Ancients:NEAR EAST or EGYPT. Ca. 5th-4th centuries BC.\nAR tetradrachm (26mm, 18.50 gm, 3h). NGC MS 5/5 - 4/5.",
      "description": "",
      "hammer_price_usd": 990.0,
      "currency_original": "USD",
      "price_original": 990.0,
      "buyers_premium_included": false,
      "sale_date": "2020-04-27",
      "image_url": "https://dyn1.heritagestatic.com/ha?p=2-2-0-7-5-22075954&w=120&h=300&it=product",
      "ngc": {
        "verified": false,
        "cert_number": null,
        "grade": "MS",
        "grade_numeric": 5,
        "strike_score": 5,
        "surface_score": 4,
        "details_grade": null,
        "certification_url": null,
        "grading_service": "ngc"
      },
      "metadata": {
        "mint": "",
        "weight_g": null,
        "diameter_mm": null,
        "obverse_desc": null,
        "reverse_desc": null
      }
    },
    {
      "id": "heritage-c7e05dca82d5",
      "source": "heritage",
      "listing_type": "auction_realized",
      "lot_url": "https://coins.ha.com/itm/ancients/greek/ancients-near-east-or-egypt-ca-5th-4th-centuries-bc-ar-tetradrachm-24mm-1549-gm-4h-ngc-au-5-5-2-5/a/3073-32155.s?ic4=ListView-ShortDescription-071515",
      "title": "Ancients:NEAR EAST or EGYPT. Ca. 5th-4th centuries BC.\nAR tetradrachm (24mm, 15.49 gm, 4h). NGC AU 5/5 - 2/5.",
      "description": "",
      "hammer_price_usd": 480.0,
      "currency_original": "USD",
      "price_original": 480.0,
      "buyers_premium_included": false,
      "sale_date": "2019-04-29",
      "image_url": "https://dyn1.heritagestatic.com/ha?p=2-0-8-0-1-20801109&w=120&h=300&it=product",
      "ngc": {
        "verified": false,
        "cert_number": null,
        "grade": "AU",
        "grade_numeric": 5,
        "strike_score": 5,
        "surface_score": 2,
        "details_grade": null,
        "certification_url": null,
        "grading_service": "ngc"
      },
      "metadata": {
        "mint": "",
        "weight_g": null,
        "diameter_mm": null,
        "obverse_desc": null,
        "reverse_desc": null
      }
    },
    {
      "id": "heritage-5e436bd48d8c",
      "source": "heritage",
      "listing_type": "auction_realized",
      "lot_url": "https://coins.ha.com/itm/ancients/roman-provincial/ancients-egypt-alexandria-annia-faustina-ad-221-bi-tetradrachm-24mm-1408-gm-11h-ngc-vf-5-5-3-5/a/3071-32185.s?ic4=ListView-ShortDescription-071515",
      "title": "Ancients:EGYPT. Alexandria. Annia Faustina (AD 221). BI\ntetradrachm (24mm, 14.08 gm, 11h). NGC VF 5/5 - 3/5.",
      "description": "",
      "hammer_price_usd": 1320.0,
      "currency_original": "USD",
      "price_original": 1320.0,
      "buyers_premium_included": false,
      "sale_date": "2019-01-07",
      "image_url": "https://dyn1.heritagestatic.com/ha?p=1-9-5-2-1-19521291&w=120&h=300&it=product",
      "ngc": {
        "verified": false,
        "cert_number": null,
        "grade": "VF",
        "grade_numeric": 5,
        "strike_score": 5,
        "surface_score": 3,
        "details_grade": null,
        "certification_url": null,
        "grading_service": "ngc"
      },
      "metadata": {
        "mint": "",
        "weight_g": null,
        "diameter_mm": null,
        "obverse_desc": null,
        "reverse_desc": null
      }
    },
    {
      "id": "heritage-f6907d17c540",
      "source": "heritage",
      "listing_type": "auction_realized",
      "lot_url": "https://coins.ha.com/itm/ancients/roman-provincial/ancients-egypt-alexandria-zenobia-usurper-ad-268-272-bi-tetradrachm-20mm-924-gm-1h-ngc-au-5-5-3-5/a/3071-32223.s?ic4=ListView-ShortDescription-071515",
      "title": "Ancients:EGYPT. Alexandria. Zenobia (usurper, AD\n268-272). BI tetradrachm (20mm, 9.24 gm, 1h). NGC AU 5/5 - 3/5.",
      "description": "",
      "hammer_price_usd": 3600.0,
      "currency_original": "USD",
      "price_original": 3600.0,
      "buyers_premium_included": false,
      "sale_date": "2019-01-07",
      "image_url": "https://dyn1.heritagestatic.com/ha?p=1-9-5-2-1-19521124&w=120&h=300&it=product",
      "ngc": {
        "verified": false,
        "cert_number": null,
        "grade": "AU",
        "grade_numeric": 5,
        "strike_score": 5,
        "surface_score": 3,
        "details_grade": null,
        "certification_url": null,
        "grading_service": "ngc"
      },
      "metadata": {
        "mint": "",
        "weight_g": null,
        "diameter_mm": null,
        "obverse_desc": null,
        "reverse_desc": null
      }
    },
    {
      "id": "heritage-db95567f3ea4",
      "source": "heritage",
      "listing_type": "auction_realized",
      "lot_url": "https://coins.ha.com/itm/ancients/greek/ancients-near-east-or-egypt-ca-5th-4th-centuries-bc-ar-tetradrachm-24mm-1715-gm-11h-ngc-ms-5-5-4-5/a/3071-33206.s?ic4=ListView-ShortDescription-071515",
      "title": "Ancients:NEAR EAST or EGYPT. Ca. 5th-4th centuries BC.\nAR tetradrachm (24mm, 17.15 gm, 11h). NGC MS 5/5 - 4/5.",
      "description": "",
      "hammer_price_usd": 1320.0,
      "currency_original": "USD",
      "price_original": 1320.0,
      "buyers_premium_included": false,
      "sale_date": "2019-01-07",
      "image_url": "https://dyn1.heritagestatic.com/ha?p=1-9-5-2-8-19528506&w=120&h=300&it=product",
      "ngc": {
        "verified": false,
        "cert_number": null,
        "grade": "MS",
        "grade_numeric": 5,
        "strike_score": 5,
        "surface_score": 4,
        "details_grade": null,
        "certification_url": null,
        "grading_service": "ngc"
      },
      "metadata": {
        "mint": "",
        "weight_g": null,
        "diameter_mm": null,
        "obverse_desc": null,
        "reverse_desc": null
      }
    },
    {
      "id": "heritage-c6a05be1cec8",
      "source": "heritage",
      "listing_type": "auction_realized",
      "lot_url": "https://coins.ha.com/itm/ancients/greek/ancients-near-east-or-egypt-ca-5th-4th-centuries-bc-ar-tetradrachm-25mm-1720-gm-6h-ngc-ms-5-5-4-5/a/3071-33207.s?ic4=ListView-ShortDescription-071515",
      "title": "Ancients:NEAR EAST or EGYPT. Ca. 5th-4th centuries BC.\nAR tetradrachm (25mm, 17.20 gm, 6h). NGC MS 5/5 - 4/5.",
      "description": "",
      "hammer_price_usd": 2040.0,
      "currency_original": "USD",
      "price_original": 2040.0,
      "buyers_premium_included": false,
      "sale_date": "2019-01-07",
      "image_url": "https://dyn1.heritagestatic.com/ha?p=1-9-5-2-8-19528424&w=120&h=300&it=product",
      "ngc": {
        "verified": false,
        "cert_number": null,
        "grade": "MS",
        "grade_numeric": 5,
        "strike_score": 5,
        "surface_score": 4,
        "details_grade": null,
        "certification_url": null,
        "grading_service": "ngc"
      },
      "metadata": {
        "mint": "",
        "weight_g": null,
        "diameter_mm": null,
        "obverse_desc": null,
        "reverse_desc": null
      }
    }
  ]
}